topaz/__init__.py
topaz/topaz.py
topaz_api-0.0.6.dist-info/licenses/LICENSE
topaz_api-0.0.6.dist-info/METADATA
topaz_api-0.0.6.dist-info/WHEEL
topaz_api-0.0.6.dist-info/top_level.txt
topaz_api-0.0.6.dist-info/RECORD
