Metadata-Version: 2.4
Name: Topaz_api
Version: 0.0.6
Summary: A Python wrapper for the GRV Topaz API
Author-email: Ivan Zhou <ivan.zhou49@gmail.com>
Project-URL: Homepage, https://github.com/pypa/sampleproject
Project-URL: Issues, https://github.com/pypa/sampleproject/issues
Classifier: Programming Language :: Python :: 3
Classifier: License :: OSI Approved :: MIT License
Classifier: Operating System :: OS Independent
Requires-Python: >=3.8
License-File: LICENSE
Requires-Dist: pandas>=2.1.3
Requires-Dist: requests>=2.31.0
Dynamic: license-file
